segdex/__init__.py
segdex/segregation_index.py
tests/test.py
segdex-0.1.1.dist-info/LICENSE.txt
segdex-0.1.1.dist-info/METADATA
segdex-0.1.1.dist-info/WHEEL
segdex-0.1.1.dist-info/top_level.txt
segdex-0.1.1.dist-info/RECORD
